balena/__init__.py
balena/auth.py
balena/balena_auth.py
balena/builder.py
balena/dependent_resource.py
balena/exceptions.py
balena/hup.py
balena/logs.py
balena/models/__init__.py
balena/models/api_key.py
balena/models/application.py
balena/models/billing.py
balena/models/config.py
balena/models/credit_bundle.py
balena/models/device.py
balena/models/device_type.py
balena/models/history.py
balena/models/image.py
balena/models/key.py
balena/models/organization.py
balena/models/os.py
balena/models/release.py
balena/models/service.py
balena/pine.py
balena/resources.py
balena/settings.py
balena/twofactor_auth.py
balena/types/__init__.py
balena/types/models.py
balena/utils.py
balena_sdk-15.1.4.dist-info/LICENSE
balena_sdk-15.1.4.dist-info/METADATA
balena_sdk-15.1.4.dist-info/WHEEL
balena_sdk-15.1.4.dist-info/RECORD
