Metadata-Version: 2.1
Name: balena-sdk
Version: 15.1.4
Summary: 
License: Apache-2.0
Author: Balena
Author-email: info@balena.io
Requires-Python: >=3.8.1,<4.0.0
Classifier: License :: OSI Approved :: Apache Software License
Classifier: Programming Language :: Python :: 3
Classifier: Programming Language :: Python :: 3.9
Classifier: Programming Language :: Python :: 3.10
Classifier: Programming Language :: Python :: 3.11
Requires-Dist: PyJWT (>=2.0.0)
Requires-Dist: Twisted (>=18.7.0)
Requires-Dist: deprecated (>=1.2.13,<2.0.0)
Requires-Dist: pine-client
Requires-Dist: pyOpenSSL (>=18.0.0)
Requires-Dist: ratelimit (>=2.2.1,<3.0.0)
Requires-Dist: requests (>=2.19.1)
Requires-Dist: semver (>=3.0.0,<4.0.0)
Requires-Dist: service-identity
Requires-Dist: typing_extensions
